woningwaardering/__init__.py
woningwaardering/_logging.py
woningwaardering/_setup.py
woningwaardering/_version.py
woningwaardering/_woningwaardering.py
woningwaardering/py.typed
woningwaardering/data/corop/corop.generated.csv
woningwaardering/stelsels/__init__.py
woningwaardering/stelsels/_dev_utils.py
woningwaardering/stelsels/criterium_id.py
woningwaardering/stelsels/stelsel.py
woningwaardering/stelsels/stelselgroep.py
woningwaardering/stelsels/utils.py
woningwaardering/stelsels/gedeelde_logica/__init__.py
woningwaardering/stelsels/gedeelde_logica/bijzondere_voorzieningen/__init__.py
woningwaardering/stelsels/gedeelde_logica/bijzondere_voorzieningen/bijzondere_voorzieningen.py
woningwaardering/stelsels/gedeelde_logica/energieprestatie/__init__.py
woningwaardering/stelsels/gedeelde_logica/energieprestatie/energieprestatie.py
woningwaardering/stelsels/gedeelde_logica/gemeenschappelijke_parkeerruimten/__init__.py
woningwaardering/stelsels/gedeelde_logica/gemeenschappelijke_parkeerruimten/gemeenschappelijke_parkeerruimten.py
woningwaardering/stelsels/gedeelde_logica/keuken/__init__.py
woningwaardering/stelsels/gedeelde_logica/keuken/keuken.py
woningwaardering/stelsels/gedeelde_logica/oppervlakte_van_overige_ruimten/__init__.py
woningwaardering/stelsels/gedeelde_logica/oppervlakte_van_overige_ruimten/oppervlakte_van_overige_ruimten.py
woningwaardering/stelsels/gedeelde_logica/oppervlakte_van_vertrekken/__init__.py
woningwaardering/stelsels/gedeelde_logica/oppervlakte_van_vertrekken/oppervlakte_van_vertrekken.py
woningwaardering/stelsels/gedeelde_logica/prijsopslag_monumenten/__init__.py
woningwaardering/stelsels/gedeelde_logica/prijsopslag_monumenten/prijsopslag_monumenten.py
woningwaardering/stelsels/gedeelde_logica/sanitair/__init__.py
woningwaardering/stelsels/gedeelde_logica/sanitair/sanitair.py
woningwaardering/stelsels/gedeelde_logica/verkoeling_en_verwarming/__init__.py
woningwaardering-4.1.0.dist-info/licenses/LICENSE
woningwaardering-4.1.0.dist-info/METADATA
woningwaardering-4.1.0.dist-info/WHEEL
woningwaardering-4.1.0.dist-info/top_level.txt
woningwaardering-4.1.0.dist-info/RECORD
