Metadata-Version: 2.4
Name: woningwaardering
Version: 4.1.0
Summary: Berekent de punten van een woning op basis van het woningwaarderingsstelsel.
Author-email: Woonstad Rotterdam <info@woonstadrotterdam.nl>, Ben Verhees <ben.verhees@woonstadrotterdam.nl>, Tiddo Loos <tiddo.loos@woonstadrotterdam.nl>, Tomer Gabay <tomer.gabay@woonstadrotterdam.nl>
Project-URL: Homepage, https://github.com/woonstadrotterdam/woningwaardering
Project-URL: Issues, https://github.com/woonstadrotterdam/woningwaardering/issues
Keywords: woning,waardering,stelsel,woningwaarderingsstelsel,wws
Classifier: Programming Language :: Python :: 3.10
Classifier: Programming Language :: Python :: 3.11
Classifier: Programming Language :: Python :: 3.12
Classifier: License :: OSI Approved :: MIT License
Classifier: Operating System :: OS Independent
Requires-Python: >=3.10
License-File: LICENSE
Requires-Dist: pydantic>=2.10
Requires-Dist: loguru>=0.7
Requires-Dist: PyYAML>=6.0
Requires-Dist: prettytable>=3.12
Requires-Dist: pandas>=2.2
Requires-Dist: requests>=2.31
Requires-Dist: types-pyyaml>=6.0
Provides-Extra: test
Requires-Dist: pre-commit>=3.3; extra == "test"
Requires-Dist: ruff>=0.5; extra == "test"
Requires-Dist: pytest>=8.3; extra == "test"
Requires-Dist: pytest-cov>=5.0; extra == "test"
Requires-Dist: types-requests>=2.32; extra == "test"
Requires-Dist: types-python-dateutil>=2.9; extra == "test"
Provides-Extra: dev
Requires-Dist: aiohttp>=3.11; extra == "dev"
Requires-Dist: woningwaardering[test]; extra == "dev"
Requires-Dist: woningwaardering[monumenten]; extra == "dev"
Requires-Dist: datamodel-code-generator[http]>=0.25.6; extra == "dev"
Requires-Dist: unidecode>=1.3; extra == "dev"
Requires-Dist: jinja2>=3.1; extra == "dev"
Requires-Dist: libcst==1.4; extra == "dev"
Requires-Dist: requests>=2.31; extra == "dev"
Requires-Dist: inquirer>=3.4; extra == "dev"
Requires-Dist: tomli>=2.2; extra == "dev"
Provides-Extra: monumenten
Requires-Dist: monumenten>=0.3; extra == "monumenten"
Dynamic: license-file
